LICENSE.txt
README.md
setup.cfg
setup.py
wizzi_utils/__init__.py
wizzi_utils.egg-info/PKG-INFO
wizzi_utils.egg-info/SOURCES.txt
wizzi_utils.egg-info/dependency_links.txt
wizzi_utils.egg-info/requires.txt
wizzi_utils.egg-info/top_level.txt
wizzi_utils/json/__init__.py
wizzi_utils/json/json_tools.py
wizzi_utils/json/test/__init__.py
wizzi_utils/json/test/test_json_tools.py
wizzi_utils/misc/__init__.py
wizzi_utils/misc/misc_tools.py
wizzi_utils/misc/test/__init__.py
wizzi_utils/misc/test/test_misc_tools.py
wizzi_utils/models/__init__.py
wizzi_utils/models/base_models.py
wizzi_utils/models/labels_bank.py
wizzi_utils/models/models_configs.py
wizzi_utils/models/cv2_models/__init__.py
wizzi_utils/models/cv2_models/object_detection.py
wizzi_utils/models/cv2_models/pose_detection.py
wizzi_utils/models/cv2_models/tracking.py
wizzi_utils/models/test/__init__.py
wizzi_utils/models/test/shared_code_for_tests.py
wizzi_utils/models/test/test_cv2_od.py
wizzi_utils/models/test/test_cv2_pd.py
wizzi_utils/models/test/test_cv2_tracking.py
wizzi_utils/models/test/test_models.py
wizzi_utils/models/test/test_tflite_od.py
wizzi_utils/models/test/test_tflite_pd.py
wizzi_utils/models/tflite_models/__init__.py
wizzi_utils/models/tflite_models/object_detection.py
wizzi_utils/models/tflite_models/pose_detection.py
wizzi_utils/open_cv/__init__.py
wizzi_utils/open_cv/open_cv_tools.py
wizzi_utils/open_cv/test/__init__.py
wizzi_utils/open_cv/test/test_open_cv_tools.py
wizzi_utils/pyplot/__init__.py
wizzi_utils/pyplot/pyplot_tools.py
wizzi_utils/pyplot/test/__init__.py
wizzi_utils/pyplot/test/test_pyplot_tools.py
wizzi_utils/socket/__init__.py
wizzi_utils/socket/socket_tools.py
wizzi_utils/socket/test/__init__.py
wizzi_utils/socket/test/test_socket_tools.py
wizzi_utils/tflite/__init__.py
wizzi_utils/tflite/tflite_tools.py
wizzi_utils/tflite/test/__init__.py
wizzi_utils/tflite/test/test_tflite.py
wizzi_utils/torch/__init__.py
wizzi_utils/torch/torch_tools.py
wizzi_utils/torch/test/__init__.py
wizzi_utils/torch/test/test_torch_tools.py
wizzi_utils/tts/__init__.py
wizzi_utils/tts/tts.py
wizzi_utils/tts/test/__init__.py
wizzi_utils/tts/test/test_tts.py
