Metadata-Version: 2.1
Name: wizzi-utils
Version: 7.2.2
Summary: Debugging tools and fast coding
Home-page: https://github.com/2easy4wizzi/2021wizzi_utils
Download-URL: https://github.com/2easy4wizzi/2021wizzi_utils/archive/refs/tags/v_7.2.2.tar.gz
Author: Gilad Eini
Author-email: giladEini@gmail.com
License: MIT
Keywords: debugging tools,json,open cv,pyplot,socket,torch,tf lite
Platform: windows
Classifier: Development Status :: 4 - Beta
Classifier: Intended Audience :: Developers
Classifier: Topic :: Software Development :: Build Tools
Classifier: License :: OSI Approved :: MIT License
Classifier: Programming Language :: Python :: 3.6
License-File: LICENSE.txt
